proportions/__init__.py
proportions/aggregation/__init__.py
proportions/aggregation/average_posterior.py
proportions/aggregation/mc_intervals.py
proportions/aggregation/moment_matching.py
proportions/aggregation/theta_distribution.py
proportions/core/__init__.py
proportions/core/models.py
proportions/diagnostics/__init__.py
proportions/diagnostics/comparison.py
proportions/diagnostics/coverage.py
proportions/diagnostics/data.py
proportions/diagnostics/evidence.py
proportions/diagnostics/importance_sampling.py
proportions/diagnostics/visualization.py
proportions/distributions/__init__.py
proportions/distributions/beta.py
proportions/distributions/truncated_beta.py
proportions/inference/__init__.py
proportions/inference/clopper_pearson.py
proportions/inference/conditional.py
proportions/inference/empirical_bayes.py
proportions/inference/fisher_test.py
proportions/inference/hierarchical_bayes.py
proportions/inference/single_proportion.py
proportions/inference/single_theta.py
proportions/inference/uncoupled_thetas.py
proportions/priors/__init__.py
proportions/priors/fitting.py
proportions/priors/specification.py
proportions/tests/__init__.py
proportions/tests/conftest.py
proportions/utils/__init__.py
proportions/validation/__init__.py
proportions/visualization/__init__.py
proportions/visualization/posterior_plots.py
proportions-0.3.5.dist-info/licenses/LICENSE
proportions-0.3.5.dist-info/METADATA
proportions-0.3.5.dist-info/WHEEL
proportions-0.3.5.dist-info/top_level.txt
proportions-0.3.5.dist-info/RECORD
