Metadata-Version: 2.4
Name: proportions
Version: 0.3.5
Summary: A comprehensive library for Bayesian and frequentist inference on binomial proportions (grouped and single) with truncated Beta prior support
Author-email: Javier Movellan <jrmovellan@gmail.com>
License-Expression: MIT
Project-URL: Homepage, https://gitlab.com/movellan/proportions
Project-URL: Repository, https://gitlab.com/movellan/proportions
Project-URL: Documentation, https://gitlab.com/movellan/proportions
Keywords: bayesian,statistics,proportions,beta-binomial,hierarchical-models
Classifier: Development Status :: 3 - Alpha
Classifier: Intended Audience :: Science/Research
Classifier: Programming Language :: Python :: 3
Classifier: Programming Language :: Python :: 3.10
Classifier: Programming Language :: Python :: 3.11
Classifier: Programming Language :: Python :: 3.12
Classifier: Topic :: Scientific/Engineering :: Mathematics
Requires-Python: >=3.10
License-File: LICENSE
Requires-Dist: numpy>=1.24.0
Requires-Dist: scipy>=1.10.0
Requires-Dist: pandas>=2.0.0
Requires-Dist: pydantic>=2.0.0
Requires-Dist: matplotlib>=3.7.0
Requires-Dist: pytest>=7.4.0
Requires-Dist: pytest-cov>=4.1.0
Provides-Extra: dev
Requires-Dist: ruff>=0.1.0; extra == "dev"
Requires-Dist: mypy>=1.5.0; extra == "dev"
Requires-Dist: black>=23.0.0; extra == "dev"
Provides-Extra: notebooks
Requires-Dist: jupyter>=1.0.0; extra == "notebooks"
Requires-Dist: jupyterlab>=4.0.0; extra == "notebooks"
Provides-Extra: viz
Requires-Dist: plotly>=5.14.0; extra == "viz"
Requires-Dist: seaborn>=0.12.0; extra == "viz"
Provides-Extra: docs
Requires-Dist: sphinx>=7.0.0; extra == "docs"
Requires-Dist: sphinx-rtd-theme>=1.3.0; extra == "docs"
Requires-Dist: nbsphinx>=0.9.0; extra == "docs"
Provides-Extra: all
Requires-Dist: proportions[dev,docs,notebooks,viz]; extra == "all"
Dynamic: license-file
